skope_rules_pyspark/__init__.py
skope_rules_pyspark/skope_rules.py
skope_rules_pyspark-0.1.2.dist-info/METADATA
skope_rules_pyspark-0.1.2.dist-info/WHEEL
skope_rules_pyspark-0.1.2.dist-info/licenses/LICENSE
skope_rules_pyspark-0.1.2.dist-info/RECORD
