Metadata-Version: 2.4
Name: skope-rules-pyspark
Version: 0.1.2
Summary: An implementation of Skope Rules for binary classification and regression using PySpark
Project-URL: Homepage, https://github.com/mickaelassaraf/skope-rules-pyspark
Project-URL: Repository, https://github.com/mickaelassaraf/skope-rules-pyspark
Author-email: Mickael Assaraf <mickael.assaraf@gmail.com>
License: MIT License
License-File: LICENSE
Keywords: classification,machine-learning,pyspark,regression,rules
Classifier: License :: OSI Approved :: MIT License
Classifier: Operating System :: OS Independent
Classifier: Programming Language :: Python :: 3
Classifier: Programming Language :: Python :: 3.7
Classifier: Programming Language :: Python :: 3.8
Classifier: Programming Language :: Python :: 3.9
Classifier: Programming Language :: Python :: 3.10
Classifier: Programming Language :: Python :: 3.11
Requires-Python: >=3.7
Requires-Dist: numpy>=1.21.6
Requires-Dist: pyspark>=3.0.0
